patternly/__init__.py
patternly/_utils.py
patternly/detection.py
patternly-0.0.33.dist-info/LICENSE
patternly-0.0.33.dist-info/METADATA
patternly-0.0.33.dist-info/WHEEL
patternly-0.0.33.dist-info/top_level.txt
patternly-0.0.33.dist-info/RECORD
