Metadata-Version: 2.1
Name: patternly
Version: 0.0.33
Summary: A tool for detecting anomalies in time series data
Home-page: https://github.com/zeroknowledgediscovery/mantis
Author: @zedlab_
Author-email: ishanu@uchicago.edu
License: LICENSE
Download-URL: https://github.com/zeroknowledgediscovery/mantis/archive/0.0.33.tar.gz
Keywords: anomaly detection,timeseries,model-free,adaptive
Platform: UNKNOWN
Classifier: Development Status :: 4 - Beta
Classifier: Intended Audience :: Developers
Classifier: Intended Audience :: Science/Research
Classifier: Topic :: Scientific/Engineering :: Information Analysis
Classifier: Topic :: Software Development :: Libraries
Classifier: License :: OSI Approved :: MIT License
Classifier: Programming Language :: Python :: 3.6
Requires-Python: >=3.6
Requires-Dist: scikit-learn
Requires-Dist: scipy
Requires-Dist: numpy
Requires-Dist: pandas
Requires-Dist: dill
Requires-Dist: zedsuite (>=0.0.4)
